{
  "package": "freshket-sense-v155-phase22-1-ai-proxy-default",
  "version": "155.22.1",
  "baseline": "v155-phase22-olive-chat-v2",
  "productBaseline": "v155-phase6.2-chat-grounding",
  "notes": [
    "Olive Chat v2 cross-scope context router",
    "concise answer policy",
    "portfolio/team GMV rankings exposed to chat",
    "no runtime changes outside chat and service-worker cache bump",
    "Default Cloudflare AI proxy URL baked into app config so mobile/new devices do not require localStorage setup"
  ]
}
